django_fast_builder
