Metadata-Version: 2.1
Name: django-fast-builder
Version: 0.2
Summary: Quick deployment of a Django project
Author-email: sergey_wilson@mail.ru
